technicalindicator/__init__.py
technicalindicator-0.0.1.dist-info/METADATA
technicalindicator-0.0.1.dist-info/WHEEL
technicalindicator-0.0.1.dist-info/top_level.txt
technicalindicator-0.0.1.dist-info/RECORD
