Metadata-Version: 2.1
Name: technicalindicator
Version: 0.0.1
Summary: The TechnicalIndicator library provides a set of technical indicators used by traders in Python
Home-page: UNKNOWN
Author: Nguyen Truong Long
Author-email: contact@nguyentruonglong.com
License: UNKNOWN
Platform: UNKNOWN
Classifier: Programming Language :: Python :: 3
Classifier: License :: OSI Approved :: GNU General Public License v3 or later (GPLv3+)
Classifier: Operating System :: OS Independent
Requires-Dist: pandas (>=1.4.2)
